odata_v4_query/__init__.py
odata_v4_query/definitions.py
odata_v4_query/errors.py
odata_v4_query/filter_parser.py
odata_v4_query/filter_tokenizer.py
odata_v4_query/query_parser.py
odata_v4_query/utils/__init__.py
odata_v4_query/utils/_func.py
odata_v4_query/utils/beanie.py
odata_v4_query/utils/pymongo.py
odata_v4_query/utils/sqlalchemy.py
odata_v4_query/utils/filter_parsers/__init__.py
odata_v4_query/utils/filter_parsers/base_filter_parser.py
odata_v4_query/utils/filter_parsers/mongo_filter_parser.py
odata_v4_query/utils/filter_parsers/sql_filter_parser.py
odata_v4_query-0.4.1.dist-info/licenses/LICENSE.md
odata_v4_query-0.4.1.dist-info/METADATA
odata_v4_query-0.4.1.dist-info/WHEEL
odata_v4_query-0.4.1.dist-info/top_level.txt
odata_v4_query-0.4.1.dist-info/RECORD
