Metadata-Version: 2.4
Name: odata-v4-query
Version: 0.4.1
Summary: A lightweight, simple and fast parser for OData V4 query options supporting standard query parameters. Provides helper functions to apply OData V4 query options to ORM/ODM queries such as SQLAlchemy, PyMongo and Beanie.
Author-email: Dairo Mosquera <dairoandres115@outlook.com>
Project-URL: Homepage, https://github.com/daireto/odata-v4-query
Project-URL: Issues, https://github.com/daireto/odata-v4-query/issues
Project-URL: Repository, https://github.com/daireto/odata-v4-query
Keywords: odata-v4-query,odata-query-parser,tokenizer-parser,wrapper
Classifier: Programming Language :: Python :: 3.10
Classifier: Programming Language :: Python :: 3.11
Classifier: Programming Language :: Python :: 3.12
Classifier: Programming Language :: Python :: 3.13
Classifier: Programming Language :: Python :: 3.14
Classifier: License :: OSI Approved :: MIT License
Classifier: Operating System :: OS Independent
Classifier: Intended Audience :: Developers
Requires-Python: >=3.10
License-File: LICENSE.md
Provides-Extra: all
Requires-Dist: beanie>=1.23.0; extra == "all"
Requires-Dist: pymongo>=4.3.3; extra == "all"
Requires-Dist: sqlalchemy>=2.0.0; extra == "all"
Provides-Extra: beanie
Requires-Dist: beanie>=1.23.0; extra == "beanie"
Provides-Extra: pymongo
Requires-Dist: pymongo>=4.3.3; extra == "pymongo"
Provides-Extra: sqlalchemy
Requires-Dist: sqlalchemy>=2.0.0; extra == "sqlalchemy"
Dynamic: license-file
